logjsonfmt/__init__.py
logjsonfmt/logjsonfmt.py
logjsonfmt-0.0.2.dist-info/LICENSE
logjsonfmt-0.0.2.dist-info/WHEEL
logjsonfmt-0.0.2.dist-info/METADATA
logjsonfmt-0.0.2.dist-info/RECORD
