Metadata-Version: 2.1
Name: logjsonfmt
Version: 0.0.2
Summary: python logging json formatter
Author: Bin Wen
Author-email: caowb@pillar-biosciences.com
Classifier: License :: OSI Approved :: MIT License
Classifier: Operating System :: OS Independent
Classifier: Programming Language :: Python
Classifier: Programming Language :: Python :: 3.7
Classifier: Programming Language :: Python :: 3.8
Classifier: Programming Language :: Python :: 3.9
